destiny_api_client/__init__.py
destiny_api_client/client.py
destiny_api_client/request_models/__init__.py
destiny_api_client/response_models/__init__.py
destiny_api_client-2022.7.3.dist-info/LICENSE
destiny_api_client-2022.7.3.dist-info/METADATA
destiny_api_client-2022.7.3.dist-info/WHEEL
destiny_api_client-2022.7.3.dist-info/top_level.txt
destiny_api_client-2022.7.3.dist-info/RECORD
